fortnite_api/__init__.py
fortnite_api/abc.py
fortnite_api/account.py
fortnite_api/aes.py
fortnite_api/all.py
fortnite_api/asset.py
fortnite_api/banner.py
fortnite_api/client.py
fortnite_api/creator_code.py
fortnite_api/enums.py
fortnite_api/errors.py
fortnite_api/flags.py
fortnite_api/http.py
fortnite_api/images.py
fortnite_api/map.py
fortnite_api/new.py
fortnite_api/new_display_asset.py
fortnite_api/news.py
fortnite_api/playlist.py
fortnite_api/proxies.py
fortnite_api/py.typed
fortnite_api/shop.py
fortnite_api/stats.py
fortnite_api/utils.py
fortnite_api/cosmetics/__init__.py
fortnite_api/cosmetics/br.py
fortnite_api/cosmetics/car.py
fortnite_api/cosmetics/common.py
fortnite_api/cosmetics/instrument.py
fortnite_api/cosmetics/lego_kit.py
fortnite_api/cosmetics/track.py
fortnite_api/cosmetics/variants/__init__.py
fortnite_api/cosmetics/variants/bean.py
fortnite_api/cosmetics/variants/lego.py
fortnite_api-3.2.1.dist-info/LICENSE
fortnite_api-3.2.1.dist-info/METADATA
fortnite_api-3.2.1.dist-info/WHEEL
fortnite_api-3.2.1.dist-info/top_level.txt
fortnite_api-3.2.1.dist-info/RECORD
