Metadata-Version: 2.1
Name: fortnite-api
Version: 3.2.1
Summary: A python wrapper for Fortnite-API.com
Author-email: Luc1412 <Luc1412.lh@gmail.com>, Trevor Flahardy <trevorflahardy@gmail.com>
License: MIT License
Project-URL: Home Page, https://github.com/Fortnite-API/py-wrapper
Project-URL: Issues, https://github.com/Fortnite-API/py-wrapper/issues
Project-URL: Documentation, https://fortnite-api.readthedocs.io/en/rewrite/
Keywords: fortnite,fortnite-api.com,shop,cosmetics,fortnite api,fortnite shop
Classifier: License :: OSI Approved :: MIT License
Classifier: Intended Audience :: Developers
Classifier: Natural Language :: English
Classifier: Operating System :: OS Independent
Classifier: Programming Language :: Python :: 3.9
Classifier: Programming Language :: Python :: 3.10
Classifier: Programming Language :: Python :: 3.11
Classifier: Programming Language :: Python :: 3.12
Classifier: Programming Language :: Python :: 3.13
Classifier: Topic :: Internet
Classifier: Topic :: Software Development :: Libraries
Classifier: Topic :: Software Development :: Libraries :: Python Modules
Classifier: Topic :: Utilities
Requires-Python: >=3.9.0
License-File: LICENSE
Requires-Dist: requests>=2.22.0
Requires-Dist: aiohttp<4.0.0,>=3.9.0
Requires-Dist: typing_extensions
Provides-Extra: tests
Requires-Dist: pytest; extra == "tests"
Requires-Dist: pytest-asyncio; extra == "tests"
Requires-Dist: pytest-cov; extra == "tests"
Requires-Dist: python-dotenv; extra == "tests"
Requires-Dist: pytest-mock; extra == "tests"
Provides-Extra: docs
Requires-Dist: sphinx; extra == "docs"
Requires-Dist: sphinxcontrib_trio; extra == "docs"
Requires-Dist: sphinxcontrib-websupport; extra == "docs"
Requires-Dist: typing-extensions; extra == "docs"
Requires-Dist: furo; extra == "docs"
Requires-Dist: sphinx-copybutton; extra == "docs"
Provides-Extra: dev
Requires-Dist: black; extra == "dev"
Requires-Dist: isort; extra == "dev"
Requires-Dist: discord.py; extra == "dev"
Requires-Dist: pyright; extra == "dev"
Requires-Dist: pre-commit; extra == "dev"
Provides-Extra: speed
Requires-Dist: orjson; extra == "speed"
